app/libs/cls.py
app/libs/func.py
app/libs/ppinfo.py
app/ppcheck.py
pp_check-0.1.19.dist-info/METADATA
pp_check-0.1.19.dist-info/WHEEL
pp_check-0.1.19.dist-info/entry_points.txt
pp_check-0.1.19.dist-info/RECORD
